hydraulic/__init__.py
hydraulic/core.py
hydraulic/fluids.py
hydraulic/pipes.py
hydraulic/thermal.py
hydraulic-0.2.0.dist-info/LICENSE
hydraulic-0.2.0.dist-info/METADATA
hydraulic-0.2.0.dist-info/WHEEL
hydraulic-0.2.0.dist-info/top_level.txt
hydraulic-0.2.0.dist-info/RECORD
