Metadata-Version: 2.1
Name: hydraulic
Version: 0.2.0
Summary: A 1D hydraulic simulator in python. 
Home-page: https://github.com/Dessia_tech/hydraulic
Author: Dessia Technologies
Author-email: root@dessia.tech
License: LGPL v3
Keywords: hydraulics,hydraulic
Platform: UNKNOWN
Classifier: Topic :: Scientific/Engineering
Classifier: Development Status :: 3 - Alpha
License-File: LICENSE
Requires-Dist: numpy
Requires-Dist: matplotlib
Requires-Dist: scipy
Requires-Dist: dessia-common (>=0.10.0)
Requires-Dist: volmdlr (>0.8.0)
